wled2graph-0.1.9.dist-info/METADATA
wled2graph-0.1.9.dist-info/WHEEL
wled2graph-0.1.9.dist-info/entry_points.txt
wled2graph/__init__.py
wled2graph/args.py
wled2graph/graphs.py
wled2graph/main.py
wled2graph/template.py
wled2graph/utils.py
wled2graph/wled.py
wled2graph-0.1.9.dist-info/RECORD
