Metadata-Version: 2.1
Name: wled2graph
Version: 0.1.9
Summary: wled2graph supports a table and graphs of FPS and other data from multiple WLED endpoints in real-time via a browser interface
Author-Email: bigredfrog <big.red.frog@gmail.com>
License: MIT
Requires-Python: <4.0,>=3.12
Requires-Dist: requests~=2.0
Requires-Dist: icmplib~=3.0
Requires-Dist: bokeh~=3.0
